eai_commons/__init__.py
eai_commons/cffi_client.py
eai_commons/logging.py
eai_commons/s3_client.py
eai_commons/auth/__init__.py
eai_commons/auth/jwt.py
eai_commons/auth/oauth2.py
eai_commons/error/__init__.py
eai_commons/error/base.py
eai_commons/error/errors.py
eai_commons/fastapi/__init__.py
eai_commons/fastapi/exception_handler.py
eai_commons/fastapi/middleware.py
eai_commons/utils/__init__.py
eai_commons/utils/auth.py
eai_commons/utils/cryptor.py
eai_commons/utils/env.py
eai_commons/utils/file.py
eai_commons/utils/func.py
eai_commons/utils/rate_limit.py
eai_commons/utils/strings.py
eai_commons/utils/sync.py
eai_commons/utils/time.py
eai_commons/utils/tracker.py
eai_commons-0.0.7.dist-info/METADATA
eai_commons-0.0.7.dist-info/WHEEL
eai_commons-0.0.7.dist-info/top_level.txt
eai_commons-0.0.7.dist-info/RECORD
